lumiera/__init__.py
lumiera/cli.py
lumiera/ansiColors/ansi_tuner.py
lumiera/ansiColors/ansi_tuner_raw.py
lumiera/ansiColors/catppuccino-frape-mocha
lumiera/ansiColors/catppuccino-frape-mocha.json
lumiera/ansiColors/palette.txt
lumiera/ansiColors/palette1.txt
lumiera/ansiColors/suhail-xcode-darkhc.json
lumiera/ansiColors/terminal_sexy.py
lumiera/backup/__init__.py
lumiera/backup/jobs.py
lumiera/data/__init__.py
lumiera/data/create_subset.py
lumiera/data/extract_course.py
lumiera/data/generate_desc.py
lumiera/data/ml_vfx.json
lumiera/data/split_payload.py
lumiera/devutils/__init__.py
lumiera/devutils/custom_tree.py
lumiera/devutils/pretty_json.py
lumiera/devutils/resize_pdf.py
lumiera/devutils/seq_renamer.py
lumiera/export/__init__.py
lumiera/export/project.py
lumiera/pypi/__init__.py
lumiera/pypi/availability.py
lumiera/pypi/yank.py
lumiera/scrapers/__init__.py
lumiera/scrapers/extract_lessons.py
lumiera/scrapers/rebelway_dl.py
lumiera/scrapers/report_sources.py
lumiera/scrapers/udemy_curriculum.py
lumiera/tests/__init__.py
lumiera/tests/test_imgseg.py
lumiera/tests/test_predict.py
lumiera-0.1.12.dist-info/METADATA
lumiera-0.1.12.dist-info/WHEEL
lumiera-0.1.12.dist-info/entry_points.txt
lumiera-0.1.12.dist-info/RECORD
