Metadata-Version: 2.4
Name: lumiera
Version: 0.1.12
Summary: Swiss‑army toolbox CLI (successor to pythonKitchen)
Author-email: Suhail <suhailece@gmail.com>
Requires-Python: <4.0.0,>=3.11.0
Requires-Dist: beautifulsoup4<5.0.0,>=4.13.4
Requires-Dist: browser-cookie3<0.21.0,>=0.20.1
Requires-Dist: jinja2<4.0.0,>=3.1.6
Requires-Dist: notion-client<3.0.0,>=2.3.0
Requires-Dist: oauthmanager<0.2.0,>=0.1.1
Requires-Dist: openai<2.0.0,>=1.76.0
Requires-Dist: openpyxl<4.0.0,>=3.1.5
Requires-Dist: pandas<3.0.0,>=2.2.3
Requires-Dist: pillow<12.0.0,>=11.2.1
Requires-Dist: pypdf<6.0.0,>=5.5.0
Requires-Dist: pytesseract<0.4.0,>=0.3.13
Requires-Dist: python-dotenv<2.0.0,>=1.1.0
Requires-Dist: pyyaml<7.0.0,>=6.0.2
Requires-Dist: requests<3.0.0,>=2.32.3
Requires-Dist: selenium<5.0.0,>=4.31.0
Requires-Dist: spotipy<3.0.0,>=2.25.1
Requires-Dist: tabulate<0.10.0,>=0.9.0
Requires-Dist: webdriver-manager<5.0.0,>=4.0.2
Provides-Extra: dev
Requires-Dist: build<2.0.0,>=1.2.2.post1; extra == 'dev'
Requires-Dist: twine<7.0.0,>=6.1.0; extra == 'dev'
